texesm/__init__.py
texesm/py.typed
texesm/texmodules.py
texesm-0.1.0.dist-info/METADATA
texesm-0.1.0.dist-info/WHEEL
texesm-0.1.0.dist-info/RECORD
